fhlmi-0.43.0.dist-info/licenses/LICENSE
lmi/__init__.py
lmi/constants.py
lmi/cost_tracker.py
lmi/embeddings.py
lmi/exceptions.py
lmi/llms.py
lmi/py.typed
lmi/rate_limiter.py
lmi/types.py
lmi/utils.py
lmi/version.py
fhlmi-0.43.0.dist-info/METADATA
fhlmi-0.43.0.dist-info/WHEEL
fhlmi-0.43.0.dist-info/top_level.txt
fhlmi-0.43.0.dist-info/RECORD
