Metadata-Version: 2.4
Name: fhlmi
Version: 0.43.0
Summary: A client to provide LLM responses for FutureHouse applications.
Author-email: FutureHouse technical staff <hello@futurehouse.org>
License:                                  Apache License
Project-URL: issues, https://github.com/Future-House/ldp/packages/lmi/issues
Project-URL: repository, https://github.com/Future-House/ldp/packages/lmi
Classifier: Intended Audience :: Developers
Classifier: License :: OSI Approved :: Apache Software License
Classifier: Operating System :: OS Independent
Classifier: Programming Language :: Python :: 3 :: Only
Classifier: Programming Language :: Python :: 3.11
Classifier: Programming Language :: Python :: 3.12
Classifier: Programming Language :: Python :: 3.13
Classifier: Programming Language :: Python
Classifier: Topic :: Scientific/Engineering :: Artificial Intelligence
Requires-Python: >=3.11
License-File: LICENSE
Requires-Dist: coredis
Requires-Dist: fhaviary>=0.14.0
Requires-Dist: limits>=4.8
Requires-Dist: litellm>=1.75.6
Requires-Dist: pydantic>=2.10.1,~=2.0
Requires-Dist: tiktoken>=0.4.0
Requires-Dist: typing-extensions; python_version <= "3.11"
Provides-Extra: dev
Requires-Dist: fhaviary[xml]; extra == "dev"
Requires-Dist: fhlmi[image,local,progress,typing,vcr]; extra == "dev"
Requires-Dist: google-auth>=2; extra == "dev"
Requires-Dist: google-cloud-storage>=3; extra == "dev"
Requires-Dist: httpx-aiohttp; extra == "dev"
Requires-Dist: ipython>=8; extra == "dev"
Requires-Dist: litellm>=1.80.10; extra == "dev"
Requires-Dist: mypy>=1.8; extra == "dev"
Requires-Dist: pre-commit>=3.4; extra == "dev"
Requires-Dist: pylint-pydantic; extra == "dev"
Requires-Dist: pytest-asyncio; extra == "dev"
Requires-Dist: pytest-recording; extra == "dev"
Requires-Dist: pytest-rerunfailures; extra == "dev"
Requires-Dist: pytest-subtests; extra == "dev"
Requires-Dist: pytest-sugar; extra == "dev"
Requires-Dist: pytest-timer[colorama]; extra == "dev"
Requires-Dist: pytest-xdist; extra == "dev"
Requires-Dist: pytest>=8; extra == "dev"
Requires-Dist: python-dotenv; extra == "dev"
Requires-Dist: refurb>=2; extra == "dev"
Requires-Dist: typeguard; extra == "dev"
Provides-Extra: image
Requires-Dist: pillow>=10.3.0; extra == "image"
Provides-Extra: local
Requires-Dist: numpy; extra == "local"
Requires-Dist: sentence-transformers; extra == "local"
Provides-Extra: progress
Requires-Dist: tqdm; extra == "progress"
Provides-Extra: typing
Requires-Dist: types-tqdm; extra == "typing"
Provides-Extra: vcr
Requires-Dist: vcrpy>=8; extra == "vcr"
Dynamic: license-file
